{"name": "\u65af\u79d1\u7279\u00b7\u6ce2\u7279", "roles": ["\u6f14\u5458", "\u914d\u97f3"], "title": "\u65af\u79d1\u7279\u00b7\u6ce2\u7279\uff08\u540c\u540d\uff09\u7f8e\u56fd,\u5185\u5e03\u62c9\u65af\u52a0\u5dde,\u5965\u9a6c\u54c8\u5f71\u89c6\u6f14\u5458", "url": "https://movie.douban.com/celebrity/1009308/", "abstract": "", "author": null, "uri": "douban://douban.com/celebrity/1009308?subject_id=27214999", "cover_url": "https://img9.doubanio.com/view/celebrity/s_ratio_celebrity/public/p6997.webp", "avatar": {"large": "https://img9.doubanio.com/view/celebrity/s_ratio_celebrity/public/p6997.webp", "normal": "https://img9.doubanio.com/view/celebrity/s_ratio_celebrity/public/p6997.webp"}, "type": "celebrity", "id": "1009308", "sharing_url": "https://www.douban.com/doubanapp/dispatch?uri=/celebrity/1009308/", "movies": [{"id": "1937401", "title": "K\u6b4c\u60c5\u4eba", "original_title": "Music and Lyrics", "year": "2007", "is_tv": false, "rating": {"count": 86546, "max": 10, "star_count": 4.0, "value": 7.5}, "poster": "https://img9.doubanio.com/view/photo/s_ratio_poster/public/p477610353.webp"}, {"id": "2230926", "title": "\u706f\u7ea2\u9152\u7eff\u6740\u4eba\u591c", "original_title": "Prom Night", "year": "2008", "is_tv": false, "rating": {"count": 2316, "max": 10, "star_count": 2.5, "value": 4.8}, "poster": "https://img9.doubanio.com/view/photo/s_ratio_poster/public/p1208893235.webp"}, {"id": "1938109", "title": "\u673a\u5668\u8089\u9e21 \u7b2c\u4e00\u5b63", "original_title": "Robot Chicken Season 1", "year": "2005", "is_tv": true, "rating": {"count": 1537, "max": 10, "star_count": 4.5, "value": 8.8}, "poster": "https://img9.doubanio.com/view/photo/m_ratio_poster/public/p2514499559.webp"}, {"id": "26758798", "title": "\u5929\u874e \u7b2c\u4e09\u5b63", "original_title": "Scorpion Season 3", "year": "2016", "is_tv": true, "rating": {"count": 2777, "max": 10, "star_count": 3.5, "value": 7.3}, "poster": "https://img9.doubanio.com/view/photo/m_ratio_poster/public/p2575728934.webp"}, {"id": "34915194", "title": "\u5947\u6ce2\u548c\u795e\u5947\u52a8\u7269\u7684\u65f6\u4ee3 \u7b2c\u4e00\u5b63", "original_title": "Kipo and the Age of Wonderbeasts Season 1", "year": "2020", "is_tv": true, "rating": {"count": 433, "max": 10, "star_count": 4.0, "value": 8.4}, "poster": "https://img9.doubanio.com/view/photo/m_ratio_poster/public/p2580869910.webp"}]}