{"name": "\u8fc8\u514b\u5c14\u00b7\u5df4\u96f7\u7279", "roles": ["\u6444\u5f71", "\u7f16\u5267", "\u5bfc\u6f14"], "title": "\u8fc8\u514b\u5c14\u00b7\u5df4\u96f7\u7279\uff08\u540c\u540d\uff09\u7f8e\u56fd,\u52a0\u5229\u798f\u5c3c\u4e9a\u5dde,\u6cb3\u6ee8\u5f71\u89c6\u6f14\u5458", "url": "https://movie.douban.com/celebrity/1018609/", "abstract": "", "author": null, "uri": "douban://douban.com/celebrity/1018609?subject_id=27224333", "cover_url": "https://img9.doubanio.com/f/movie/8dd0c794499fe925ae2ae89ee30cd225750457b4/pics/movie/celebrity-default-medium.png", "avatar": {"large": "https://img9.doubanio.com/f/movie/63acc16ca6309ef191f0378faf793d1096a3e606/pics/movie/celebrity-default-large.png", "normal": "https://img9.doubanio.com/f/movie/8dd0c794499fe925ae2ae89ee30cd225750457b4/pics/movie/celebrity-default-medium.png"}, "type": "celebrity", "id": "1018609", "sharing_url": "https://www.douban.com/doubanapp/dispatch?uri=/celebrity/1018609/", "movies": [{"id": "27093132", "title": "\u9b3c\u5e99", "original_title": "Temple", "year": "2017", "is_tv": false, "rating": {"count": 671, "max": 10, "star_count": 2.0, "value": 3.8}, "poster": "https://img9.doubanio.com/view/photo/m_ratio_poster/public/p2493554167.webp"}]}