{"name": "\u8428\u7c73\u5c14\u00b7\u76d6\u4e1d\u7c73", "roles": ["\u6f14\u5458", "\u5bfc\u6f14", "\u7f16\u5267"], "title": "\u8428\u7c73\u5c14\u00b7\u76d6\u4e1d\u7c73\uff08\u540c\u540d\uff09\u6cd5\u56fd,\u5df4\u9ece\u5f71\u89c6\u6f14\u5458", "url": "https://movie.douban.com/celebrity/1028743/", "abstract": "", "author": null, "uri": "douban://douban.com/celebrity/1028743?subject_id=27234481", "cover_url": "https://img9.doubanio.com/view/celebrity/s_ratio_celebrity/public/p17588.webp", "avatar": {"large": "https://img9.doubanio.com/view/celebrity/s_ratio_celebrity/public/p17588.webp", "normal": "https://img9.doubanio.com/view/celebrity/s_ratio_celebrity/public/p17588.webp"}, "type": "celebrity", "id": "1028743", "sharing_url": "https://www.douban.com/doubanapp/dispatch?uri=/celebrity/1028743/", "movies": [{"id": "4583146", "title": "\u5df4\u9ece\u4e94\u533a\u7684\u5973\u4eba", "original_title": "La femme du V\u00e8me", "year": "2011", "is_tv": false, "rating": {"count": 1442, "max": 10, "star_count": 3.0, "value": 6.3}, "poster": "https://img9.doubanio.com/view/photo/s_ratio_poster/public/p1590899189.webp"}, {"id": "26616708", "title": "\u6c34\u4e2d\u6548\u5e94", "original_title": "L'effet aquatique", "year": "2016", "is_tv": false, "rating": {"count": 583, "max": 10, "star_count": 3.5, "value": 6.8}, "poster": "https://img9.doubanio.com/view/photo/m_ratio_poster/public/p2459002438.webp"}, {"id": "5153600", "title": "\u4ea4\u54cd\u73ed", "original_title": "La m\u00e9lodie", "year": "2017", "is_tv": false, "rating": {"count": 440, "max": 10, "star_count": 3.0, "value": 6.3}, "poster": "https://img9.doubanio.com/view/photo/m_ratio_poster/public/p2516331790.webp"}, {"id": "20435079", "title": "\u9b42\u5f52\u6545\u91cc \u7b2c\u4e00\u5b63", "original_title": "Les Revenants Season 1", "year": "2012", "is_tv": true, "rating": {"count": 5275, "max": 10, "star_count": 4.0, "value": 8.4}, "poster": "https://img9.doubanio.com/view/photo/m_ratio_poster/public/p2173794080.webp"}, {"id": "11596343", "title": "\u8499\u7279\u52d2\u4f0a\u7684\u5973\u738b", "original_title": "Queen of Montreuil", "year": "2012", "is_tv": false, "rating": {"count": 62, "max": 10, "star_count": 3.5, "value": 7.3}, "poster": "https://img9.doubanio.com/view/photo/m_ratio_poster/public/p1867822246.webp"}, {"id": "30259222", "title": "\u5949\u571f\u5730\u4e4b\u540d", "original_title": "Au nom de la terre", "year": "2019", "is_tv": false, "rating": {"count": 126, "max": 10, "star_count": 3.5, "value": 7.0}, "poster": "https://img9.doubanio.com/view/photo/m_ratio_poster/public/p2562180363.webp"}, {"id": "35558634", "title": "\u50cf\u8fd9\u6837\u7684\u590f\u5929", "original_title": "Un \u00e9t\u00e9 comme \u00e7a", "year": "2022", "is_tv": false, "rating": {"count": 316, "max": 10, "star_count": 3.0, "value": 5.9}, "poster": "https://img9.doubanio.com/view/photo/m_ratio_poster/public/p2856637465.webp"}]}