{"name": "\u70ed\u62c9\u5c14\u00b7\u514b\u74e6\u5179\u514b", "roles": ["\u5bfc\u6f14", "\u6f14\u5458", "\u7f16\u5267", "\u526f\u5bfc\u6f14"], "title": "\u70ed\u62c9\u5c14\u00b7\u514b\u74e6\u5179\u514b\uff08\u540c\u540d\uff09\u6cd5\u56fd,\u5df4\u9ece\u5f71\u89c6\u6f14\u5458", "url": "https://movie.douban.com/celebrity/1045533/", "abstract": "", "author": null, "uri": "douban://douban.com/celebrity/1045533?subject_id=27251290", "cover_url": "https://img9.doubanio.com/view/celebrity/s_ratio_celebrity/public/p17587.webp", "avatar": {"large": "https://img9.doubanio.com/view/celebrity/s_ratio_celebrity/public/p17587.webp", "normal": "https://img9.doubanio.com/view/celebrity/s_ratio_celebrity/public/p17587.webp"}, "type": "celebrity", "id": "1045533", "sharing_url": "https://www.douban.com/doubanapp/dispatch?uri=/celebrity/1045533/", "movies": [{"id": "1302271", "title": "\u7684\u58eb\u901f\u90122", "original_title": "Taxi 2", "year": "2000", "is_tv": false, "rating": {"count": 43355, "max": 10, "star_count": 4.0, "value": 7.8}, "poster": "https://img9.doubanio.com/view/photo/s_ratio_poster/public/p1339506474.webp"}, {"id": "1308156", "title": "\u7684\u58eb\u901f\u90123", "original_title": "Taxi 3", "year": "2003", "is_tv": false, "rating": {"count": 32545, "max": 10, "star_count": 3.5, "value": 7.3}, "poster": "https://img9.doubanio.com/view/photo/s_ratio_poster/public/p2529661996.webp"}, {"id": "1306518", "title": "\u7eff\u82a5\u5211\u8b66", "original_title": "Wasabi", "year": "2001", "is_tv": false, "rating": {"count": 27787, "max": 10, "star_count": 3.5, "value": 7.1}, "poster": "https://img9.doubanio.com/view/photo/s_ratio_poster/public/p823947361.webp"}, {"id": "1929443", "title": "\u7684\u58eb\u901f\u90124", "original_title": "Taxi 4", "year": "2007", "is_tv": false, "rating": {"count": 30568, "max": 10, "star_count": 3.5, "value": 7.0}, "poster": "https://img9.doubanio.com/view/photo/s_ratio_poster/public/p903648927.webp"}]}