{"name": "\u74e6\u59ae\u838e\u00b7\u8d1d\u5c14\u00b7\u5361\u6d1b\u5a01", "roles": ["\u6f14\u5458", "\u914d\u97f3"], "title": "\u74e6\u59ae\u838e\u00b7\u8d1d\u5c14\u00b7\u5361\u6d1b\u5a01\uff08\u540c\u540d\uff09\u7f8e\u56fd,\u4fc4\u4ea5\u4fc4\u5dde\u514b\u5229\u592b\u5170\u5e02\u5f71\u89c6\u6f14\u5458", "url": "https://movie.douban.com/celebrity/1066980/", "uri": "douban://douban.com/celebrity/1066980?subject_id=27272723", "avatar": {"large": "https://img9.doubanio.com/view/celebrity/raw/public/p1538790744.91.jpg", "normal": "https://img9.doubanio.com/view/celebrity/raw/public/p1538790744.91.jpg"}, "sharing_url": "https://www.douban.com/doubanapp/dispatch?uri=/celebrity/1066980/", "type": "celebrity", "id": "1066980", "latin_name": "Vanessa Bell Calloway", "movies": [{"id": "3657538", "title": "\u62a4\u58eb\u957f\u7684\u6545\u4e8b \u7b2c\u4e00\u5b63", "original_title": "Hawthorne Season 1", "year": "2009", "is_tv": true, "rating": null, "poster": "https://img9.doubanio.com/view/photo/m_ratio_poster/public/p1073265652.webp"}]}