{"name": "\u5927\u6cc9\u6d0b", "roles": ["\u6f14\u5458", "\u914d\u97f3", "\u7f16\u5267", "\u5bfc\u6f14"], "title": "\u5927\u6cc9\u6d0b\uff08\u540c\u540d\uff09\u65e5\u672c,\u5317\u6d77\u9053,Ebetsu\u5f71\u89c6\u6f14\u5458", "url": "https://movie.douban.com/celebrity/1184188/", "abstract": "\u51fa\u751f\u4e8e\u65e5\u672c\u5317\u6d77\u9053\u6c5f\u522b\u5e02\uff0c\u96b6\u5c5eCREATIVE OFFICE CUE\u4e8b\u52a1\u6240\u7684\u6f14\u5458\u3002\u8eab\u9ad8178\u5398\u7c73\uff0c\u8840\u578b\u4e3aB\u578b\u30022009\u5e745\u67082\u65e5...", "author": null, "uri": "douban://douban.com/celebrity/1184188?subject_id=27390130", "cover_url": "https://img1.doubanio.com/view/celebrity/s_ratio_celebrity/public/p1368494074.17.webp", "avatar": {"large": "https://img1.doubanio.com/view/celebrity/s_ratio_celebrity/public/p1368494074.17.webp", "normal": "https://img1.doubanio.com/view/celebrity/s_ratio_celebrity/public/p1368494074.17.webp"}, "type": "celebrity", "id": "1184188", "sharing_url": "https://www.douban.com/doubanapp/dispatch?uri=/celebrity/1184188/", "movies": [{"id": "2295776", "title": "\u8304\u5b50\uff1a\u65c5\u884c\u7bb1\u4e2d\u7684\u5019\u9e1f", "original_title": "\u8304\u5b50 \u30b9\u30fc\u30c4\u30b1\u30fc\u30b9\u306e\u6e21\u308a\u9ce5", "year": "2007", "is_tv": false, "rating": {"count": 1593, "max": 10, "star_count": 4.0, "value": 8.4}, "poster": "https://img1.doubanio.com/view/photo/s_ratio_poster/public/p2525291499.webp"}, {"id": "25969201", "title": "\u6295\u9760\u5973\u4e0e\u51fa\u8d70\u7537", "original_title": "\u99c6\u8fbc\u307f\u5973\u3068\u99c6\u51fa\u3057\u7537", "year": "2015", "is_tv": false, "rating": {"count": 13348, "max": 10, "star_count": 4.0, "value": 8.2}, "poster": "https://img2.doubanio.com/view/photo/s_ratio_poster/public/p2233635683.webp"}, {"id": "5279593", "title": "\u5e78\u798f\u7684\u9762\u5305", "original_title": "\u3057\u3042\u308f\u305b\u306e\u30d1\u30f3", "year": "2012", "is_tv": false, "rating": {"count": 16562, "max": 10, "star_count": 4.0, "value": 7.6}, "poster": "https://img9.doubanio.com/view/photo/s_ratio_poster/public/p1421989266.webp"}, {"id": "3077700", "title": "\u653e\u8bfe\u540e", "original_title": "\u30a2\u30d5\u30bf\u30fc\u30b9\u30af\u30fc\u30eb", "year": "2008", "is_tv": false, "rating": {"count": 4332, "max": 10, "star_count": 4.0, "value": 7.5}, "poster": "https://img9.doubanio.com/view/photo/s_ratio_poster/public/p2191406455.webp"}, {"id": "30156101", "title": "\u9ed1\u4e95\u6237\u7591\u6848", "original_title": "\u9ed2\u4e95\u6238\u6bba\u3057", "year": "2018", "is_tv": false, "rating": {"count": 3831, "max": 10, "star_count": 3.5, "value": 7.4}, "poster": "https://img9.doubanio.com/view/photo/s_ratio_poster/public/p2519819673.webp"}, {"id": "27191173", "title": "\u604b\u5982\u96e8\u6b62", "original_title": "\u604b\u306f\u96e8\u4e0a\u304c\u308a\u306e\u3088\u3046\u306b", "year": "2018", "is_tv": false, "rating": {"count": 12060, "max": 10, "star_count": 3.5, "value": 7.4}, "poster": "https://img9.doubanio.com/view/photo/s_ratio_poster/public/p2511831665.webp"}, {"id": "24870630", "title": "\u6674\u5929\u9739\u96f3", "original_title": "\u9752\u5929\u306e\u9739\u9742", "year": "2014", "is_tv": false, "rating": {"count": 1433, "max": 10, "star_count": 3.5, "value": 7.2}, "poster": "https://img9.doubanio.com/view/photo/s_ratio_poster/public/p2170194168.webp"}, {"id": "1796010", "title": "\u52c7\u8005\u4f20\u8bf4", "original_title": "\u30d6\u30ec\u30a4\u30d6\u30fb\u30b9\u30c8\u30fc\u30ea\u30fc", "year": "2006", "is_tv": false, "rating": {"count": 1171, "max": 10, "star_count": 3.5, "value": 7.3}, "poster": "https://img9.doubanio.com/view/photo/s_ratio_poster/public/p656813327.webp"}, {"id": "10833867", "title": "\u6e05\u987b\u4f1a\u8bae", "original_title": "\u6e05\u9808\u4f1a\u8b70", "year": "2013", "is_tv": false, "rating": {"count": 5926, "max": 10, "star_count": 3.5, "value": 7.2}, "poster": "https://img9.doubanio.com/view/photo/s_ratio_poster/public/p2018581855.webp"}, {"id": "25899379", "title": "\u8bf7\u53eb\u6211\u82f1\u96c4", "original_title": "\u30a2\u30a4\u30a2\u30e0\u30a2\u30d2\u30fc\u30ed\u30fc", "year": "2015", "is_tv": false, "rating": {"count": 52666, "max": 10, "star_count": 3.5, "value": 7.2}, "poster": "https://img9.doubanio.com/view/photo/s_ratio_poster/public/p2395074307.webp"}, {"id": "25870671", "title": "\u9ece\u660e\u7684\u6c99\u8036", "original_title": "\u30c8\u30ef\u30a4\u30e9\u30a4\u30c8 \u3055\u3055\u3089\u3055\u3084", "year": "2014", "is_tv": false, "rating": {"count": 3380, "max": 10, "star_count": 3.5, "value": 7.0}, "poster": "https://img9.doubanio.com/view/photo/s_ratio_poster/public/p2201501453.webp"}, {"id": "10430704", "title": "\u5927\u5bb6\u65e9\u4e0a\u597d\uff01", "original_title": "\u30b0\u30c3\u30e2\u30fc\u30a8\u30d3\u30a2\u30f3\uff01", "year": "2012", "is_tv": false, "rating": {"count": 1694, "max": 10, "star_count": 3.5, "value": 6.8}, "poster": "https://img9.doubanio.com/view/photo/s_ratio_poster/public/p1692765629.webp"}, {"id": "6023509", "title": "\u6ce1\u5427\u4fa6\u63a2", "original_title": "\u63a2\u5075\u306fBAR\u306b\u3044\u308b", "year": "2011", "is_tv": false, "rating": {"count": 1644, "max": 10, "star_count": 3.5, "value": 6.5}, "poster": "https://img9.doubanio.com/view/photo/s_ratio_poster/public/p1180529683.webp"}, {"id": "24719840", "title": "\u6ce1\u5427\u4fa6\u63a23", "original_title": "\u63a2\u5075\u306fBAR\u306b\u3044\u308b3", "year": "2017", "is_tv": false, "rating": {"count": 1138, "max": 10, "star_count": 3.0, "value": 6.3}, "poster": "https://img9.doubanio.com/view/photo/s_ratio_poster/public/p2505419712.webp"}, {"id": "30203549", "title": "\u4e09\u66f4\u534a\u591c\u5c45\u7136\u8981\u9999\u8549 \u7231\u7684\u771f\u5b9e\u6545\u4e8b", "original_title": "\u3053\u3093\u306a\u591c\u66f4\u3051\u306b\u30d0\u30ca\u30ca\u304b\u3088 \u611b\u3057\u304d\u5b9f\u8a71", "year": "2018", "is_tv": false, "rating": {"count": 1174, "max": 10, "star_count": 3.5, "value": 6.6}, "poster": "https://img9.doubanio.com/view/photo/m_ratio_poster/public/p2537936671.webp"}, {"id": "25728003", "title": "\u8461\u8404\u7684\u773c\u6cea", "original_title": "\u3076\u3069\u3046\u306e\u306a\u307f\u3060", "year": "2014", "is_tv": false, "rating": {"count": 844, "max": 10, "star_count": 3.0, "value": 6.0}, "poster": "https://img9.doubanio.com/view/photo/m_ratio_poster/public/p2191655941.webp"}, {"id": "30217015", "title": "\u5144\u59b9", "original_title": "\u3042\u306b\u3044\u3082\u3046\u3068", "year": "2018", "is_tv": false, "rating": {"count": 733, "max": 10, "star_count": 3.5, "value": 7.2}, "poster": "https://img9.doubanio.com/view/photo/m_ratio_poster/public/p2524005653.webp"}, {"id": "11600075", "title": "\u6ce1\u5427\u4fa6\u63a22", "original_title": "\u63a2\u5075\u306fBAR\u306b\u3044\u308b2", "year": "2013", "is_tv": false, "rating": {"count": 735, "max": 10, "star_count": 3.5, "value": 6.6}, "poster": "https://img9.doubanio.com/view/photo/m_ratio_poster/public/p1853098868.webp"}, {"id": "33371682", "title": "\u4e09\u56fd\u5fd7\u65b0\u89e3", "original_title": "\u65b0\u89e3\u91c8\u30fb\u4e09\u570b\u5fd7", "year": "2020", "is_tv": false, "rating": {"count": 646, "max": 10, "star_count": 2.5, "value": 5.3}, "poster": "https://img9.doubanio.com/view/photo/m_ratio_poster/public/p2624681380.webp"}, {"id": "27605696", "title": "Goodbye \u4ee5\u8c0e\u8a00\u5f00\u7aef\u7684\u4eba\u751f\u559c\u5267", "original_title": "\u30b0\u30c3\u30c9\u30d0\u30a4\uff5e\u5618\u304b\u3089\u306f\u3058\u307e\u308b\u4eba\u751f\u559c\u5287\uff5e", "year": "2019", "is_tv": false, "rating": {"count": 815, "max": 10, "star_count": 3.0, "value": 6.1}, "poster": "https://img9.doubanio.com/view/photo/m_ratio_poster/public/p2575439681.webp"}, {"id": "25884841", "title": "\u771f\u7530\u4e38", "original_title": "", "year": "2016", "is_tv": true, "rating": {"count": 12694, "max": 10, "star_count": 4.5, "value": 8.7}, "poster": "https://img9.doubanio.com/view/photo/m_ratio_poster/public/p2290840913.webp"}, {"id": "30283216", "title": "\u604b\u5982\u96e8\u6b62~\u53e3\u888b\u4e2d\u7684\u613f\u671b~", "original_title": "\u604b\u306f\u96e8\u4e0a\u304c\u308a\u306e\u3088\u3046\u306b \uff5e\u30dd\u30b1\u30c3\u30c8\u306e\u4e2d\u306e\u9858\u3044\u3054\u3068\uff5e", "year": "2018", "is_tv": true, "rating": {"count": 551, "max": 10, "star_count": 3.0, "value": 6.4}, "poster": "https://img9.doubanio.com/view/photo/m_ratio_poster/public/p2559895927.webp"}, {"id": "35081499", "title": "2020\u5e74 \u4e94\u6708\u4e4b\u604b", "original_title": "2020\u5e74 \u4e94\u6708\u306e\u604b", "year": "2020", "is_tv": true, "rating": {"count": 1267, "max": 10, "star_count": 4.5, "value": 8.6}, "poster": "https://img9.doubanio.com/view/photo/m_ratio_poster/public/p2613858250.webp"}, {"id": "30464337", "title": "\u6bd4\u8d5b\u5b8c\u6bd5", "original_title": "\u30ce\u30fc\u30b5\u30a4\u30c9\u30fb\u30b2\u30fc\u30e0", "year": "2019", "is_tv": true, "rating": {"count": 1564, "max": 10, "star_count": 4.0, "value": 8.0}, "poster": "https://img9.doubanio.com/view/photo/m_ratio_poster/public/p2561935159.webp"}, {"id": "30186542", "title": "\u9519\u89c6\u753b\u7684\u5229\u7259", "original_title": "\u9a19\u3057\u7d75\u306e\u7259", "year": "2021", "is_tv": false, "rating": {"count": 1238, "max": 10, "star_count": 3.5, "value": 6.8}, "poster": "https://img9.doubanio.com/view/photo/m_ratio_poster/public/p2627545662.webp"}, {"id": "20389705", "title": "\u5408\u79df\u5c4b\u7684\u604b\u4eba", "original_title": "\u30b7\u30a7\u30a2\u30cf\u30a6\u30b9\u306e\u604b\u4eba", "year": "2013", "is_tv": true, "rating": {"count": 3738, "max": 10, "star_count": 3.0, "value": 6.4}, "poster": "https://img9.doubanio.com/view/photo/m_ratio_poster/public/p2611783633.webp"}, {"id": "25892818", "title": "\u7236\u4eb2\u7684\u80cc\u5f71", "original_title": "\u304a\u3084\u3058\u306e\u80cc\u4e2d", "year": "2014", "is_tv": true, "rating": {"count": 2816, "max": 10, "star_count": 4.0, "value": 8.3}, "poster": "https://img9.doubanio.com/view/photo/m_ratio_poster/public/p2191558340.webp"}, {"id": "26306645", "title": "\u4e0d\u4fbf\u7684\u4fbf\u5229\u5c4b", "original_title": "\u4e0d\u4fbf\u306a\u4fbf\u5229\u5c4b", "year": "2015", "is_tv": true, "rating": {"count": 2897, "max": 10, "star_count": 4.0, "value": 7.7}, "poster": "https://img9.doubanio.com/view/photo/m_ratio_poster/public/p2268560946.webp"}, {"id": "34941578", "title": "\u9570\u4ed3\u6bbf\u768413\u4eba", "original_title": "\u938c\u5009\u6bbf\u306e13\u4eba", "year": "2022", "is_tv": true, "rating": {"count": 1436, "max": 10, "star_count": 4.5, "value": 8.7}, "poster": "https://img9.doubanio.com/view/photo/m_ratio_poster/public/p2755237842.webp"}, {"id": "36251654", "title": "LAST MAN-\u5168\u76f2\u641c\u67e5\u5b98-", "original_title": "\u30e9\u30b9\u30c8\u30de\u30f3\uff0d\u5168\u76f2\u306e\u635c\u67fb\u5b98\uff0d", "year": "2023", "is_tv": true, "rating": {"count": 0, "max": 10, "star_count": 0.0, "value": 0}, "poster": "https://img9.doubanio.com/view/photo/m_ratio_poster/public/p2891073524.webp"}]}