{"name": "Adam Curry", "roles": ["\u6f14\u5458"], "title": "Adam Curry\uff08\u540c\u540d\uff09\u7f8e\u56fd,\u534e\u76db\u987f\u54e5\u4f26\u6bd4\u4e9a\u7279\u533a\u5f71\u89c6\u6f14\u5458", "url": "https://movie.douban.com/celebrity/1185894/", "uri": "douban://douban.com/celebrity/1185894?subject_id=27391838", "avatar": {"large": "https://img9.doubanio.com/view/celebrity/raw/public/p1618185127.98.jpg", "normal": "https://img9.doubanio.com/view/celebrity/raw/public/p1618185127.98.jpg"}, "sharing_url": "https://www.douban.com/doubanapp/dispatch?uri=/celebrity/1185894/", "type": "celebrity", "id": "1185894", "latin_name": "", "movies": [{"id": "1298627", "title": "\u4e0e\u9ea6\u5f53\u5a1c\u540c\u5e8a", "original_title": "Madonna: Truth or Dare", "year": "1991", "is_tv": false, "rating": {"count": 616, "max": 10, "star_count": 4.0, "value": 7.8}, "poster": "https://img9.doubanio.com/view/photo/m_ratio_poster/public/p1740076558.webp"}]}