{"name": "\u8389\u5b89\u5a1c\u00b7\u5965\u514b\u83b1\u4e3d", "roles": ["\u6f14\u5458", "\u5316\u5986"], "title": "\u8389\u5b89\u5a1c\u00b7\u5965\u514b\u83b1\u4e3d\uff08\u540c\u540d\uff09\u7231\u5c14\u5170,\u90fd\u67cf\u6797\u5f71\u89c6\u6f14\u5458", "url": "https://movie.douban.com/celebrity/1253107/", "uri": "douban://douban.com/celebrity/1253107?subject_id=27459099", "avatar": {"large": "https://img9.doubanio.com/view/celebrity/raw/public/p1566487384.92.jpg", "normal": "https://img9.doubanio.com/view/celebrity/raw/public/p1566487384.92.jpg"}, "sharing_url": "https://www.douban.com/doubanapp/dispatch?uri=/celebrity/1253107/", "type": "celebrity", "id": "1253107", "latin_name": "Liana O'Cleirigh", "movies": [{"id": "10562341", "title": "\u7406\u67e5\u505a\u4e86\u4ec0\u4e48", "original_title": "What Richard Did", "year": "2012", "is_tv": false, "rating": {"count": 84, "max": 10, "star_count": 3.0, "value": 6.2}, "poster": "https://img9.doubanio.com/view/photo/m_ratio_poster/public/p2092488932.webp"}]}