{"name": "\u7ea6\u7ff0\u00b7\u5927\u536b\u00b7\u79d1\u5c14\u65af", "roles": ["\u5bfc\u6f14", "\u5236\u7247\u4eba"], "title": "\u7ea6\u7ff0\u00b7\u5927\u536b\u00b7\u79d1\u5c14\u65af\uff08\u540c\u540d\uff09None\u5f71\u89c6\u6f14\u5458", "url": "https://movie.douban.com/celebrity/1281039/", "uri": "douban://douban.com/celebrity/1281039?subject_id=27509318", "latin_name": "John David Coles", "sharing_url": "https://www.douban.com/doubanapp/dispatch?uri=/celebrity/1281039/", "type": "celebrity", "id": "1281039", "avatar": {"large": "https://img9.doubanio.com/view/celebrity/raw/public/p1392637847.31.jpg", "normal": "https://img9.doubanio.com/view/celebrity/raw/public/p1392637847.31.jpg"}, "movies": [{"id": "10493928", "title": "\u798f\u5c14\u6469\u65af\uff1a\u57fa\u672c\u6f14\u7ece\u6cd5 \u7b2c\u4e00\u5b63", "original_title": "Elementary Season 1", "year": "2012", "is_tv": true, "rating": {"count": 50340, "max": 10, "star_count": 4.0, "value": 8.2}, "poster": "https://img9.doubanio.com/view/photo/m_ratio_poster/public/p1651018165.webp"}, {"id": "1337286", "title": "\u7edd\u671b\u4e3b\u5987 \u7b2c\u4e00\u5b63", "original_title": "Desperate Housewives Season 1", "year": "2004", "is_tv": true, "rating": {"count": 92573, "max": 10, "star_count": 4.5, "value": 8.8}, "poster": "https://img9.doubanio.com/view/photo/m_ratio_poster/public/p2190803888.webp"}, {"id": "22523356", "title": "\u7eb8\u724c\u5c4b \u7b2c\u4e8c\u5b63", "original_title": "House of Cards Season 2", "year": "2014", "is_tv": true, "rating": {"count": 106965, "max": 10, "star_count": 4.5, "value": 9.2}, "poster": "https://img9.doubanio.com/view/photo/m_ratio_poster/public/p2165497217.webp"}, {"id": "25823412", "title": "\u7eb8\u724c\u5c4b \u7b2c\u4e09\u5b63", "original_title": "House of Cards Season 3", "year": "2015", "is_tv": true, "rating": {"count": 60632, "max": 10, "star_count": 4.0, "value": 8.4}, "poster": "https://img9.doubanio.com/view/photo/m_ratio_poster/public/p2226185451.webp"}, {"id": "23776190", "title": "\u8d1d\u8328\u65c5\u9986 \u7b2c\u4e8c\u5b63", "original_title": "Bates Motel Season 2", "year": "2014", "is_tv": true, "rating": {"count": 6951, "max": 10, "star_count": 4.0, "value": 7.9}, "poster": "https://img9.doubanio.com/view/photo/m_ratio_poster/public/p2169068012.webp"}, {"id": "20515883", "title": "\u6740\u622e\u5143\u51f6", "original_title": "Those Who Kill", "year": "2014", "is_tv": true, "rating": {"count": 557, "max": 10, "star_count": 3.5, "value": 7.1}, "poster": "https://img9.doubanio.com/view/photo/m_ratio_poster/public/p2166741678.webp"}, {"id": "25800871", "title": "\u6743\u6b32 \u7b2c\u4e00\u5b63", "original_title": "Power Season 1", "year": "2014", "is_tv": true, "rating": {"count": 886, "max": 10, "star_count": 3.5, "value": 7.1}, "poster": "https://img9.doubanio.com/view/photo/m_ratio_poster/public/p2300112163.webp"}, {"id": "26030078", "title": "11.22.63", "original_title": "", "year": "2016", "is_tv": true, "rating": {"count": 5731, "max": 10, "star_count": 4.0, "value": 7.9}, "poster": "https://img9.doubanio.com/view/photo/m_ratio_poster/public/p2318164176.webp"}, {"id": "26303734", "title": "\u6885\u8d5b\u5fb7\u65af\u5148\u751f \u7b2c\u4e00\u5b63", "original_title": "Mr. Mercedes Season 1", "year": "2017", "is_tv": true, "rating": {"count": 3648, "max": 10, "star_count": 4.0, "value": 7.9}, "poster": "https://img9.doubanio.com/view/photo/m_ratio_poster/public/p2494388141.webp"}, {"id": "30172298", "title": "\u7f6a\u4eba \u7b2c\u4e8c\u5b63", "original_title": "The Sinner Season 2", "year": "2018", "is_tv": true, "rating": {"count": 963, "max": 10, "star_count": 4.0, "value": 7.6}, "poster": "https://img9.doubanio.com/view/photo/m_ratio_poster/public/p2532928742.webp"}]}