{"name": "\u59da\u5929\u5802", "roles": ["\u5bfc\u6f14"], "title": "\u59da\u5929\u5802\uff08\u540c\u540d\uff09\u5f71\u89c6\u6f14\u5458", "url": "https://movie.douban.com/celebrity/1323102/", "abstract": "", "author": null, "uri": "douban://douban.com/celebrity/1323102?subject_id=27567414", "cover_url": "https://img9.doubanio.com/f/movie/8dd0c794499fe925ae2ae89ee30cd225750457b4/pics/movie/celebrity-default-medium.png", "avatar": {"large": "https://img9.doubanio.com/f/movie/63acc16ca6309ef191f0378faf793d1096a3e606/pics/movie/celebrity-default-large.png", "normal": "https://img9.doubanio.com/f/movie/8dd0c794499fe925ae2ae89ee30cd225750457b4/pics/movie/celebrity-default-medium.png"}, "type": "celebrity", "id": "1323102", "sharing_url": "https://www.douban.com/doubanapp/dispatch?uri=/celebrity/1323102/", "movies": [{"id": "1306691", "title": "\u4f4e\u4e00\u70b9\u7684\u5929\u7a7a", "original_title": "", "year": "2003", "is_tv": false, "rating": {"count": 636, "max": 10, "star_count": 3.5, "value": 7.1}, "poster": "https://img9.doubanio.com/view/photo/m_ratio_poster/public/p2355295458.webp"}, {"id": "3025300", "title": "\u81f3\u5c0a\u98df\u738b", "original_title": "\u98df\u795e", "year": "1998", "is_tv": true, "rating": {"count": 916, "max": 10, "star_count": 3.5, "value": 6.8}, "poster": "https://img9.doubanio.com/view/photo/m_ratio_poster/public/p2496433469.webp"}]}