{"name": "Peppe Lanzetta", "roles": ["\u6f14\u5458", "\u7f16\u5267"], "title": "Peppe Lanzetta\uff08\u540c\u540d\uff09None\u5f71\u89c6\u6f14\u5458", "url": "https://movie.douban.com/celebrity/1325982/", "uri": "douban://douban.com/celebrity/1325982?subject_id=27500860", "avatar": {"large": "https://img9.doubanio.com/view/celebrity/raw/public/p1545058458.48.jpg", "normal": "https://img9.doubanio.com/view/celebrity/raw/public/p1545058458.48.jpg"}, "sharing_url": "https://www.douban.com/doubanapp/dispatch?uri=/celebrity/1325982/", "type": "celebrity", "id": "1325982", "latin_name": "", "movies": [{"id": "2080155", "title": "\u80ae\u810f\u7684\u7231\u60c5", "original_title": "L'amore molesto", "year": "1995", "is_tv": false, "rating": {"count": 620, "max": 10, "star_count": 4.0, "value": 7.7}, "poster": "https://img9.doubanio.com/view/photo/m_ratio_poster/public/p2534567717.webp"}]}