{"name": "\u4f0a\u6069\u00b7\u6258\u5c3c\u987f", "roles": ["\u5bfc\u6f14"], "title": "\u4f0a\u6069\u00b7\u6258\u5c3c\u987f\uff08\u540c\u540d\uff09None\u5f71\u89c6\u6f14\u5458", "url": "https://movie.douban.com/celebrity/1333290/", "uri": "douban://douban.com/celebrity/1333290?subject_id=27543496", "avatar": {"large": "https://img9.doubanio.com/view/celebrity/raw/public/p1586831822.91.jpg", "normal": "https://img9.doubanio.com/view/celebrity/raw/public/p1586831822.91.jpg"}, "sharing_url": "https://www.douban.com/doubanapp/dispatch?uri=/celebrity/1333290/", "type": "celebrity", "id": "1333290", "latin_name": "Ian Toynton", "movies": [{"id": "1417489", "title": "\u4f2a\u88c5\u8005 \u7b2c\u4e00\u5b63", "original_title": "The Pretender Season 1", "year": "1996", "is_tv": true, "rating": {"count": 3810, "max": 10, "star_count": 4.5, "value": 8.7}, "poster": "https://img9.doubanio.com/view/photo/m_ratio_poster/public/p2521776816.webp"}, {"id": "26992364", "title": "\u6d77\u8c79\u7a81\u51fb\u961f \u7b2c\u4e00\u5b63", "original_title": "SEAL Team Season 1", "year": "2017", "is_tv": true, "rating": {"count": 5867, "max": 10, "star_count": 4.0, "value": 8.4}, "poster": "https://img9.doubanio.com/view/photo/m_ratio_poster/public/p2497590534.webp"}, {"id": "27042735", "title": "\u6307\u5b9a\u5e78\u5b58\u8005 \u7b2c\u4e8c\u5b63", "original_title": "Designated Survivor Season 2", "year": "2017", "is_tv": true, "rating": {"count": 1915, "max": 10, "star_count": 3.5, "value": 6.6}, "poster": "https://img9.doubanio.com/view/photo/m_ratio_poster/public/p2496669222.webp"}]}