{"name": "\u82b9\u6cfd\u4f18", "roles": ["\u914d\u97f3", "\u6f14\u5458"], "title": "\u82b9\u6cfd\u4f18\uff08\u540c\u540d\uff09\u65e5\u672c,\u4e1c\u4eac\u5f71\u89c6\u6f14\u5458", "url": "https://movie.douban.com/celebrity/1341966/", "abstract": "\u65e5\u672c\u5973\u6027\u58f0\u4f18\u3001\u540c\u65f6\u4e5f\u662f\u5076\u50cf\u7ec4\u5408\u201ci\u2606Ris\u201d\u7684\u6210\u5458\u4e4b\u4e00\uff0c\u4ece\u5c5e\u4e8e81produce\u4e8b\u52a1\u6240\uff0c\u6bd5\u4e1a\u4e8e\u65e5\u672c\u5a31\u4e50\u5a92\u4f53\u603b\u5408...", "author": null, "uri": "douban://douban.com/celebrity/1341966?subject_id=27489100", "cover_url": "https://img9.doubanio.com/view/celebrity/s_ratio_celebrity/public/p6V6WwjyYLVccel_avatar_uploaded1407324254.03.webp", "avatar": {"large": "https://img9.doubanio.com/view/celebrity/s_ratio_celebrity/public/p6V6WwjyYLVccel_avatar_uploaded1407324254.03.webp", "normal": "https://img9.doubanio.com/view/celebrity/s_ratio_celebrity/public/p6V6WwjyYLVccel_avatar_uploaded1407324254.03.webp"}, "type": "celebrity", "id": "1341966", "sharing_url": "https://www.douban.com/doubanapp/dispatch?uri=/celebrity/1341966/", "movies": [{"id": "33377767", "title": "\u603b\u4e4b\u5c31\u662f\u975e\u5e38\u53ef\u7231", "original_title": "\u30c8\u30cb\u30ab\u30af\u30ab\u30ef\u30a4\u30a4", "year": "2020", "is_tv": true, "rating": {"count": 7546, "max": 10, "star_count": 4.0, "value": 7.6}, "poster": "https://img9.doubanio.com/view/photo/m_ratio_poster/public/p2615826169.webp"}, {"id": "35161232", "title": "\u5982\u679c\u70e7\u9676\u7684\u8bdd\u4e5f\u505a\u4e2a\u9a6c\u514b\u676f\u5427", "original_title": "\u3084\u304f\u306a\u3089\u30de\u30b0\u30ab\u30c3\u30d7\u3082", "year": "2021", "is_tv": true, "rating": {"count": 124, "max": 10, "star_count": 3.5, "value": 6.5}, "poster": "https://img9.doubanio.com/view/photo/m_ratio_poster/public/p2615608569.webp"}, {"id": "30132464", "title": "\u5f02\u4e16\u754c\u9b54\u738b\u4e0e\u53ec\u5524\u5c11\u5973\u7684\u5974\u96b6\u9b54\u672f", "original_title": "\u7570\u4e16\u754c\u9b54\u738b\u3068\u53ec\u559a\u5c11\u5973\u306e\u5974\u96b7\u9b54\u8853", "year": "2018", "is_tv": true, "rating": {"count": 2181, "max": 10, "star_count": 3.0, "value": 6.3}, "poster": "https://img9.doubanio.com/view/photo/m_ratio_poster/public/p2520572412.webp"}, {"id": "27197216", "title": "\u4e09\u6b21\u5143\u5973\u53cb \u7b2c\u4e00\u5b63", "original_title": "3D\u5f7c\u5973 \u30ea\u30a2\u30eb\u30ac\u30fc\u30eb", "year": "2018", "is_tv": true, "rating": {"count": 697, "max": 10, "star_count": 3.5, "value": 6.6}, "poster": "https://img9.doubanio.com/view/photo/m_ratio_poster/public/p2511337258.webp"}, {"id": "26678832", "title": "\u53cc\u661f\u4e4b\u9634\u9633\u5e08", "original_title": "\u53cc\u661f\u306e\u9670\u967d\u5e2b", "year": "2016", "is_tv": true, "rating": {"count": 2080, "max": 10, "star_count": 3.0, "value": 6.0}, "poster": "https://img9.doubanio.com/view/photo/m_ratio_poster/public/p2327887188.webp"}, {"id": "25919935", "title": "\u5173\u4e8e\u6211\u88ab\u7ed1\u67b6\u5230\u5927\u5c0f\u59d0\u5b66\u6821\u5f53\u5eb6\u6c11\u6837\u672c\u8fd9\u4ef6\u4e8b", "original_title": "\u4ffa\u304c\u304a\u5b22\u69d8\u5b66\u6821\u306b\u300c\u5eb6\u6c11\u30b5\u30f3\u30d7\u30eb\u300d\u3068\u3057\u3066\u30b2\u30c3\u30c4\u3055\u308c\u305f\u4ef6", "year": "2015", "is_tv": true, "rating": {"count": 2016, "max": 10, "star_count": 3.0, "value": 5.7}, "poster": "https://img9.doubanio.com/view/photo/m_ratio_poster/public/p2265013038.webp"}, {"id": "35033420", "title": "\u5f02\u4e16\u754c\u9b54\u738b\u4e0e\u53ec\u5524\u5c11\u5973\u7684\u5974\u96b6\u9b54\u672f\u03a9", "original_title": "\u7570\u4e16\u754c\u9b54\u738b\u3068\u53ec\u559a\u5c11\u5973\u306e\u5974\u96b7\u9b54\u8853\u03a9", "year": "2021", "is_tv": true, "rating": {"count": 484, "max": 10, "star_count": 3.0, "value": 6.4}, "poster": "https://img9.doubanio.com/view/photo/m_ratio_poster/public/p2633726960.webp"}, {"id": "30230131", "title": "\u7b28\u62d9\u4e4b\u6781\u7684\u4e0a\u91ce", "original_title": "\u4e0a\u91ce\u3055\u3093\u306f\u4e0d\u5668\u7528", "year": "2019", "is_tv": true, "rating": {"count": 2228, "max": 10, "star_count": 3.5, "value": 7.3}, "poster": "https://img9.doubanio.com/view/photo/m_ratio_poster/public/p2541864499.webp"}, {"id": "30255083", "title": "\u4e09\u6b21\u5143\u5973\u53cb \u7b2c\u4e8c\u5b63", "original_title": "3D\u5f7c\u5973 \u30ea\u30a2\u30eb\u30ac\u30fc\u30eb \u7b2c2\u30b7\u30fc\u30ba\u30f3", "year": "2019", "is_tv": true, "rating": {"count": 283, "max": 10, "star_count": 3.5, "value": 7.3}, "poster": "https://img9.doubanio.com/view/photo/m_ratio_poster/public/p2542923248.webp"}, {"id": "34931854", "title": "\u6447\u6eda\u90fd\u5e02 \u7b2c\u4e09\u5b63", "original_title": "SHOW BY ROCK!!\u307e\u3057\u3085\u307e\u3044\u308c\u3063\u3057\u3085!!", "year": "2020", "is_tv": true, "rating": {"count": 123, "max": 10, "star_count": 4.0, "value": 7.7}, "poster": "https://img9.doubanio.com/view/photo/m_ratio_poster/public/p2578964824.webp"}, {"id": "24752306", "title": "\u91ce\u826f\u795e", "original_title": "\u30ce\u30e9\u30ac\u30df", "year": "2014", "is_tv": true, "rating": {"count": 62722, "max": 10, "star_count": 4.5, "value": 8.7}, "poster": "https://img9.doubanio.com/view/photo/m_ratio_poster/public/p2166913228.webp"}, {"id": "26357796", "title": "\u91ce\u826f\u795e \u7b2c2\u5b63", "original_title": "\u30ce\u30e9\u30ac\u30df ARAGOTO", "year": "2015", "is_tv": true, "rating": {"count": 40586, "max": 10, "star_count": 4.5, "value": 9.1}, "poster": "https://img9.doubanio.com/view/photo/m_ratio_poster/public/p2272736294.webp"}]}