{"name": "Jessica Sirls", "roles": ["\u6f14\u5458", "\u5236\u7247\u4eba"], "title": "Jessica Sirls\uff08\u540c\u540d\uff09None\u5f71\u89c6\u6f14\u5458", "url": "https://movie.douban.com/celebrity/1342011/", "uri": "douban://douban.com/celebrity/1342011?subject_id=27497919", "avatar": {"large": "https://img9.doubanio.com/f/movie/63acc16ca6309ef191f0378faf793d1096a3e606/pics/movie/celebrity-default-large.png", "normal": "https://img9.doubanio.com/f/movie/8dd0c794499fe925ae2ae89ee30cd225750457b4/pics/movie/celebrity-default-medium.png"}, "sharing_url": "https://www.douban.com/doubanapp/dispatch?uri=/celebrity/1342011/", "type": "celebrity", "id": "1342011", "latin_name": "", "movies": [{"id": "22508408", "title": "\u8001\u7238\u5165\u4fb5\u8bb0", "original_title": "Dads", "year": "2013", "is_tv": true, "rating": {"count": 664, "max": 10, "star_count": 3.5, "value": 6.6}, "poster": "https://img9.doubanio.com/view/photo/m_ratio_poster/public/p2122691947.webp"}]}