{"name": "\u9a6c\u6b63\u9633", "roles": ["\u914d\u97f3"], "title": "\u9a6c\u6b63\u9633\uff08\u540c\u540d\uff09\u4e2d\u56fd,\u6cb3\u5357,\u6d1b\u9633\u5f71\u89c6\u6f14\u5458", "url": "https://movie.douban.com/celebrity/1359431/", "abstract": "\u5149\u5408\u79ef\u6728\u65b0\u58f0\u4ee3\u7b7e\u7ea6\u914d\u97f3\u6f14\u5458\uff0c\u6708\u58f0\u914d\u97f3\u793e\u793e\u957f\u3002 \u300a\u7405\u740a\u699c\u4e4b\u98ce\u8d77\u957f\u6797\u300b\u8427\u5e73\u65cc\uff08\u5218\u660a\u7136 \u9970\uff09 \u300a\u53cc\u4e16\u5ba0\u5983...", "author": null, "uri": "douban://douban.com/celebrity/1359431?subject_id=27576403", "cover_url": "https://img1.doubanio.com/view/celebrity/s_ratio_celebrity/public/p1540269715.78.webp", "avatar": {"large": "https://img1.doubanio.com/view/celebrity/s_ratio_celebrity/public/p1540269715.78.webp", "normal": "https://img1.doubanio.com/view/celebrity/s_ratio_celebrity/public/p1540269715.78.webp"}, "type": "celebrity", "id": "1359431", "sharing_url": "https://www.douban.com/doubanapp/dispatch?uri=/celebrity/1359431/", "movies": [{"id": "34908091", "title": "\u5929\u5b98\u8d50\u798f", "original_title": "", "year": "2020", "is_tv": true, "rating": {"count": 11689, "max": 10, "star_count": 4.5, "value": 9.1}, "poster": "https://img1.doubanio.com/view/photo/s_ratio_poster/public/p2621050857.webp"}, {"id": "30217371", "title": "\u52a8\u7269\u7279\u5de5\u5c40", "original_title": "", "year": "2019", "is_tv": false, "rating": {"count": 4932, "max": 10, "star_count": 3.0, "value": 6.2}, "poster": "https://img9.doubanio.com/view/photo/m_ratio_poster/public/p2580985868.webp"}, {"id": "35263119", "title": "\u5929\u5b98\u8d50\u798f \u7279\u522b\u7bc7", "original_title": "", "year": "2021", "is_tv": true, "rating": {"count": 7864, "max": 10, "star_count": 4.5, "value": 8.6}, "poster": "https://img9.doubanio.com/view/photo/m_ratio_poster/public/p2630121237.webp"}, {"id": "35874296", "title": "\u6211\u662f\u7279\u4f18\u58f0 \u5267\u56e2\u5b63", "original_title": "", "year": "2022", "is_tv": true, "rating": {"count": 739, "max": 10, "star_count": 2.5, "value": 5.3}, "poster": "https://img9.doubanio.com/view/photo/m_ratio_poster/public/p2876221509.webp"}, {"id": "34444648", "title": "\u4e09\u4f53", "original_title": "", "year": "2022", "is_tv": true, "rating": {"count": 71734, "max": 10, "star_count": 3.0, "value": 5.6}, "poster": "https://img2.doubanio.com/view/photo/m_ratio_poster/public/p2885057891.webp"}, {"id": "36093359", "title": "\u4f0d\u516d\u4e03\u4e4b\u6697\u5f71\u5bbf\u547d", "original_title": "", "year": "2023", "is_tv": true, "rating": {"count": 5861, "max": 10, "star_count": 4.5, "value": 9.0}, "poster": "https://img1.doubanio.com/view/photo/m_ratio_poster/public/p2886272760.webp"}]}