{"name": "\u533a\u6c38\u6743", "roles": ["\u6f14\u5458", "\u5176\u5b83"], "title": "\u533a\u6c38\u6743\uff08\u540c\u540d\uff09None\u5f71\u89c6\u6f14\u5458", "url": "https://movie.douban.com/celebrity/1364172/", "uri": "douban://douban.com/celebrity/1364172?subject_id=27559932", "latin_name": "Albert Au", "sharing_url": "https://www.douban.com/doubanapp/dispatch?uri=/celebrity/1364172/", "type": "celebrity", "id": "1364172", "avatar": {"large": "https://img9.doubanio.com/view/celebrity/raw/public/p1478067419.4.jpg", "normal": "https://img9.doubanio.com/view/celebrity/raw/public/p1478067419.4.jpg"}, "movies": [{"id": "26271893", "title": "12\u91d1\u9e2d", "original_title": "12\u91d1\u9d28", "year": "2015", "is_tv": false, "rating": {"count": 19280, "max": 10, "star_count": 2.5, "value": 5.3}, "poster": "https://img9.doubanio.com/view/photo/m_ratio_poster/public/p2244031573.webp"}]}