{"name": "\u4e54\u4e39\u00b7A\u00b7\u7eb3\u4ec0", "roles": ["\u6f14\u5458"], "title": "\u4e54\u4e39\u00b7A\u00b7\u7eb3\u4ec0\uff08\u540c\u540d\uff09None\u5f71\u89c6\u6f14\u5458", "url": "https://movie.douban.com/celebrity/1373103/", "uri": "douban://douban.com/celebrity/1373103?subject_id=27587392", "avatar": {"large": "https://img9.doubanio.com/view/celebrity/raw/public/p1623674860.55.jpg", "normal": "https://img9.doubanio.com/view/celebrity/raw/public/p1623674860.55.jpg"}, "sharing_url": "https://www.douban.com/doubanapp/dispatch?uri=/celebrity/1373103/", "type": "celebrity", "id": "1373103", "latin_name": "Jordan A. Nash", "movies": [{"id": "30368448", "title": "\u65e0\u9650", "original_title": "Infinite", "year": "2021", "is_tv": false, "rating": {"count": 12587, "max": 10, "star_count": 2.5, "value": 5.4}, "poster": "https://img9.doubanio.com/view/photo/m_ratio_poster/public/p2655492682.webp"}, {"id": "26791990", "title": "\u8fdc\u8d70\u9ad8\u98de", "original_title": "Come Away", "year": "2020", "is_tv": false, "rating": {"count": 437, "max": 10, "star_count": 2.0, "value": 4.1}, "poster": "https://img9.doubanio.com/view/photo/m_ratio_poster/public/p2623098438.webp"}, {"id": "26805324", "title": "\u540d\u59dd \u7b2c\u4e00\u5b63", "original_title": "Harlots Season 1", "year": "2017", "is_tv": true, "rating": {"count": 77878, "max": 10, "star_count": 4.0, "value": 8.4}, "poster": "https://img9.doubanio.com/view/photo/m_ratio_poster/public/p2466378191.webp"}]}