{"name": "\u949f\u9e23", "roles": ["\u6f14\u5458"], "title": "\u949f\u9e23\uff08\u540c\u540d\uff09None\u5f71\u89c6\u6f14\u5458", "url": "https://movie.douban.com/celebrity/1378596/", "uri": "douban://douban.com/celebrity/1378596?subject_id=27563490", "latin_name": "Ming Zhong", "sharing_url": "https://www.douban.com/doubanapp/dispatch?uri=/celebrity/1378596/", "type": "celebrity", "id": "1378596", "avatar": {"large": "https://img9.doubanio.com/view/celebrity/raw/public/p1501938909.24.jpg", "normal": "https://img9.doubanio.com/view/celebrity/raw/public/p1501938909.24.jpg"}, "movies": [{"id": "35029547", "title": "\u6c89\u9999\u5982\u5c51\u00b7\u6c89\u9999\u91cd\u534e", "original_title": "", "year": "2022", "is_tv": true, "rating": {"count": 164547, "max": 10, "star_count": 3.0, "value": 5.6}, "poster": "https://img9.doubanio.com/view/photo/m_ratio_poster/public/p2702644019.webp"}]}