{"name": "\u6c38\u91ce\u7231\u7406", "roles": ["\u914d\u97f3", "\u6f14\u5458"], "title": "\u6c38\u91ce\u7231\u7406\uff08\u540c\u540d\uff09\u65e5\u672c,\u5bab\u57ce\u5f71\u89c6\u6f14\u5458", "url": "https://movie.douban.com/celebrity/1389976/", "abstract": "\u6c38\u91ce\u7231\u7406\u662f\u65e5\u672c\u7684\u5973\u6027\u58f0\u4f18\uff0c\u5bab\u57ce\u53bf\u51fa\u8eab\u300281 Produce\u6240\u5c5e\u3002\u8840\u578bO\u578b\u3002\u300cWake Up,Girls!\u300d\u58f0\u4f18\u56e2\u961f\u4e03\u4eba\u7ec4\u5f53...", "author": null, "uri": "douban://douban.com/celebrity/1389976?subject_id=30167627", "cover_url": "https://img9.doubanio.com/view/celebrity/s_ratio_celebrity/public/p1537188533.22.webp", "avatar": {"large": "https://img9.doubanio.com/view/celebrity/s_ratio_celebrity/public/p1537188533.22.webp", "normal": "https://img9.doubanio.com/view/celebrity/s_ratio_celebrity/public/p1537188533.22.webp"}, "type": "celebrity", "id": "1389976", "sharing_url": "https://www.douban.com/doubanapp/dispatch?uri=/celebrity/1389976/", "movies": [{"id": "25766639", "title": "Wake Up, Girls! \u4e03\u4eba\u7684\u5076\u50cf", "original_title": "Wake Up, Girls! \u4e03\u4eba\u306e\u30a2\u30a4\u30c9\u30eb", "year": "2014", "is_tv": false, "rating": {"count": 744, "max": 10, "star_count": 4.0, "value": 7.6}, "poster": "https://img9.doubanio.com/view/photo/m_ratio_poster/public/p2169295314.webp"}]}