{"name": "\u94b1\u65af\u00b7\u4f69\u5c14\u591a\u83ab", "roles": ["\u6f14\u5458"], "title": "\u94b1\u65af\u00b7\u4f69\u5c14\u591a\u83ab\uff08\u540c\u540d\uff09\u82f1\u56fd\u5f71\u89c6\u6f14\u5458", "url": "https://movie.douban.com/celebrity/1408633/", "uri": "douban://douban.com/celebrity/1408633?subject_id=30426956", "avatar": {"large": "https://img9.doubanio.com/view/celebrity/raw/public/pMouFoWIv_vYcel_avatar_uploaded1546887671.18.jpg", "normal": "https://img9.doubanio.com/view/celebrity/raw/public/pMouFoWIv_vYcel_avatar_uploaded1546887671.18.jpg"}, "sharing_url": "https://www.douban.com/doubanapp/dispatch?uri=/celebrity/1408633/", "type": "celebrity", "id": "1408633", "latin_name": "Chance Perdomo", "movies": [{"id": "27595184", "title": "\u8428\u5e03\u4e3d\u5a1c\u7684\u60ca\u5fc3\u5192\u9669 \u7b2c\u4e00\u5b63", "original_title": "Chilling Adventures of Sabrina Season 1", "year": "2018", "is_tv": true, "rating": {"count": 6994, "max": 10, "star_count": 3.5, "value": 7.0}, "poster": "https://img9.doubanio.com/view/photo/m_ratio_poster/public/p2533960064.webp"}, {"id": "27595186", "title": "\u8428\u5e03\u4e3d\u5a1c\u7684\u60ca\u5fc3\u5192\u9669 \u7b2c\u4e8c\u5b63", "original_title": "Chilling Adventures of Sabrina Season 2", "year": "2019", "is_tv": true, "rating": {"count": 2773, "max": 10, "star_count": 3.5, "value": 7.3}, "poster": "https://img9.doubanio.com/view/photo/m_ratio_poster/public/p2550679141.webp"}, {"id": "30409416", "title": "\u8428\u5e03\u4e3d\u5a1c\u7684\u60ca\u5fc3\u5192\u9669 \u7b2c\u4e09\u5b63", "original_title": "Chilling Adventures of Sabrina Season 3", "year": "2020", "is_tv": true, "rating": {"count": 1962, "max": 10, "star_count": 3.5, "value": 6.7}, "poster": "https://img9.doubanio.com/view/photo/m_ratio_poster/public/p2583530125.webp"}, {"id": "35211473", "title": "V\u4e16\u4ee3", "original_title": "GEN V", "year": "2023", "is_tv": true, "rating": {"count": 0, "max": 10, "star_count": 0.0, "value": 0}, "poster": "https://img1.doubanio.com/view/photo/m_ratio_poster/public/p2898632379.webp"}]}