{"name": "\u738b\u5b9a\u534e", "roles": ["\u6f14\u5458"], "title": "\u738b\u5b9a\u534e\uff08\u540c\u540d\uff09\u4e2d\u56fd,\u6d59\u6c5f\u5f71\u89c6\u6f14\u5458", "url": "https://movie.douban.com/celebrity/1413347/", "uri": "douban://douban.com/celebrity/1413347?subject_id=33372487", "avatar": {"large": "https://img9.doubanio.com/view/celebrity/raw/public/p1579433853.99.jpg", "normal": "https://img9.doubanio.com/view/celebrity/raw/public/p1579433853.99.jpg"}, "sharing_url": "https://www.douban.com/doubanapp/dispatch?uri=/celebrity/1413347/", "type": "celebrity", "id": "1413347", "latin_name": "Dinghua Wang", "movies": [{"id": "3227289", "title": "\u4e1c\u6e2f\u8c0d\u5f71", "original_title": "", "year": "1978", "is_tv": false, "rating": {"count": 268, "max": 10, "star_count": 3.5, "value": 6.5}, "poster": "https://img9.doubanio.com/view/photo/m_ratio_poster/public/p2264829492.webp"}]}