{"name": "\u91ce\u4ea6\u5219\u884c", "roles": ["\u5bfc\u6f14"], "title": "\u91ce\u4ea6\u5219\u884c\uff08\u540c\u540d\uff09\u5f71\u89c6\u6f14\u5458", "url": "https://movie.douban.com/celebrity/1431920/", "abstract": "", "author": null, "uri": "douban://douban.com/celebrity/1431920?subject_id=34974475", "cover_url": "https://img9.doubanio.com/f/movie/8dd0c794499fe925ae2ae89ee30cd225750457b4/pics/movie/celebrity-default-medium.png", "avatar": {"large": "https://img9.doubanio.com/f/movie/63acc16ca6309ef191f0378faf793d1096a3e606/pics/movie/celebrity-default-large.png", "normal": "https://img9.doubanio.com/f/movie/8dd0c794499fe925ae2ae89ee30cd225750457b4/pics/movie/celebrity-default-medium.png"}, "type": "celebrity", "id": "1431920", "sharing_url": "https://www.douban.com/doubanapp/dispatch?uri=/celebrity/1431920/", "movies": [{"id": "25912261", "title": "\u6697\u6740\u6559\u5ba4", "original_title": "\u6697\u6bba\u6559\u5ba4", "year": "2015", "is_tv": true, "rating": {"count": 31002, "max": 10, "star_count": 4.5, "value": 8.6}, "poster": "https://img9.doubanio.com/view/photo/m_ratio_poster/public/p2218283964.webp"}, {"id": "26993066", "title": "\u9b54\u6cd5\u4f7f\u7684\u65b0\u5a18", "original_title": "\u9b54\u6cd5\u4f7f\u3044\u306e\u5ac1", "year": "2017", "is_tv": true, "rating": {"count": 6143, "max": 10, "star_count": 4.0, "value": 8.4}, "poster": "https://img9.doubanio.com/view/photo/m_ratio_poster/public/p2497954989.webp"}, {"id": "27107139", "title": "\u5996\u7cbe\u68ee\u6797\u7684\u5c0f\u4e0d\u70b9", "original_title": "\u30cf\u30af\u30e1\u30a4\u3068\u30df\u30b3\u30c1", "year": "2018", "is_tv": true, "rating": {"count": 11552, "max": 10, "star_count": 4.5, "value": 9.3}, "poster": "https://img9.doubanio.com/view/photo/m_ratio_poster/public/p2509508062.webp"}, {"id": "30163813", "title": "\u5361\u7f57\u5c14\u4e0e\u661f\u671f\u4e8c", "original_title": "\u30ad\u30e3\u30ed\u30eb\uff06\u30c1\u30e5\u30fc\u30ba\u30c7\u30a4", "year": "2019", "is_tv": true, "rating": {"count": 25092, "max": 10, "star_count": 4.5, "value": 8.5}, "poster": "https://img9.doubanio.com/view/photo/m_ratio_poster/public/p2545649085.webp"}, {"id": "27191426", "title": "\u7518\u7c95\u4e0e\u739b\u7d22\u4e39", "original_title": "\u3072\u305d\u306d\u3068\u307e\u305d\u305f\u3093", "year": "2018", "is_tv": true, "rating": {"count": 878, "max": 10, "star_count": 4.0, "value": 8.1}, "poster": "https://img9.doubanio.com/view/photo/m_ratio_poster/public/p2513160828.webp"}, {"id": "26375693", "title": "\u6697\u6740\u6559\u5ba4 \u7b2c2\u5b63", "original_title": "\u6697\u6bba\u6559\u5ba4 \u7b2c2\u671f", "year": "2016", "is_tv": true, "rating": {"count": 21879, "max": 10, "star_count": 4.5, "value": 9.2}, "poster": "https://img9.doubanio.com/view/photo/m_ratio_poster/public/p2298126991.webp"}]}