{"name": "\u9a6c\u6b47\u5c14\u00b7\u6797\u5947", "roles": ["\u6f14\u5458"], "title": "\u9a6c\u6b47\u5c14\u00b7\u6797\u5947\uff08\u540c\u540d\uff09None\u5f71\u89c6\u6f14\u5458", "url": "https://movie.douban.com/celebrity/1434179/", "uri": "douban://douban.com/celebrity/1434179?subject_id=34995221", "avatar": {"large": "https://qnmob3.doubanio.com/view/personage/raw/public/db3e6006be3f40d70c560e30ca4db764.jpg?imageView2/2/q/80/w/600/h/3000/format/webp", "normal": "https://qnmob3.doubanio.com/view/personage/raw/public/db3e6006be3f40d70c560e30ca4db764.jpg?imageView2/2/q/80/w/200/h/300/format/webp"}, "sharing_url": "https://www.douban.com/doubanapp/dispatch?uri=/celebrity/1434179/", "type": "celebrity", "id": "1434179", "latin_name": "Marshawn Lynch", "movies": [{"id": "36037265", "title": "\u57ab\u5e95\u4ff1\u4e50\u90e8", "original_title": "Bottoms", "year": "2023", "is_tv": false, "rating": {"count": 443, "max": 10, "star_count": 4.0, "value": 7.5}, "poster": "https://img1.doubanio.com/view/photo/m_ratio_poster/public/p2892948780.webp"}]}