{"name": "\u514b\u91cc\u65af\u00b7\u514b\u91cc", "roles": ["\u6f14\u5458"], "title": "\u514b\u91cc\u65af\u00b7\u514b\u91cc\uff08\u540c\u540d\uff09None\u5f71\u89c6\u6f14\u5458", "url": "https://movie.douban.com/celebrity/1467813/", "uri": "douban://douban.com/celebrity/1467813?subject_id=35762461", "latin_name": "Chris Crema", "sharing_url": "https://www.douban.com/doubanapp/dispatch?uri=/celebrity/1467813/", "type": "celebrity", "id": "1467813", "avatar": {"large": "https://img9.doubanio.com/view/personage/raw/public/d95e365a6481faf91b710afd805a6aca.jpg", "normal": "https://img9.doubanio.com/view/personage/raw/public/d95e365a6481faf91b710afd805a6aca.jpg"}, "movies": [{"id": "27044878", "title": "\u9634\u8c0b\uff1a\u4f5c\u5bb6\u4e4b\u6b7b", "original_title": "Intrigo: Death of an Author", "year": "2018", "is_tv": false, "rating": {"count": 745, "max": 10, "star_count": 3.5, "value": 6.5}, "poster": "https://img9.doubanio.com/view/photo/m_ratio_poster/public/p2528991174.webp"}]}