{"name": "Marshall Adams", "roles": ["\u6444\u5f71", "\u5bfc\u6f14"], "title": "Marshall Adams\uff08\u540c\u540d\uff09None\u5f71\u89c6\u6f14\u5458", "url": "https://movie.douban.com/celebrity/1470996/", "uri": "douban://douban.com/celebrity/1470996?subject_id=35879487", "avatar": {"large": "https://img9.doubanio.com/f/movie/63acc16ca6309ef191f0378faf793d1096a3e606/pics/movie/celebrity-default-large.png", "normal": "https://img9.doubanio.com/f/movie/8dd0c794499fe925ae2ae89ee30cd225750457b4/pics/movie/celebrity-default-medium.png"}, "sharing_url": "https://www.douban.com/doubanapp/dispatch?uri=/celebrity/1470996/", "type": "celebrity", "id": "1470996", "latin_name": "", "movies": [{"id": "3768108", "title": "\u72af\u7f6a\u73b0\u573a\u8c03\u67e5\uff1a\u7ebd\u7ea6 \u7b2c\u56db\u5b63", "original_title": "CSI: NY Season 4", "year": "2007", "is_tv": true, "rating": {"count": 2476, "max": 10, "star_count": 4.5, "value": 9.0}, "poster": "https://img9.doubanio.com/view/photo/m_ratio_poster/public/p2534886483.webp"}, {"id": "6794395", "title": "\u72af\u7f6a\u73b0\u573a\u8c03\u67e5\uff1a\u7ebd\u7ea6 \u7b2c\u516b\u5b63", "original_title": "CSI: NY Season 8", "year": "2011", "is_tv": true, "rating": {"count": 1741, "max": 10, "star_count": 4.5, "value": 8.5}, "poster": "https://img9.doubanio.com/view/photo/m_ratio_poster/public/p2534886670.webp"}, {"id": "3735976", "title": "\u72af\u7f6a\u73b0\u573a\u8c03\u67e5\uff1a\u7ebd\u7ea6 \u7b2c\u4e94\u5b63", "original_title": "CSI: NY Season 5", "year": "2008", "is_tv": true, "rating": {"count": 2503, "max": 10, "star_count": 4.5, "value": 9.0}, "poster": "https://img9.doubanio.com/view/photo/m_ratio_poster/public/p2867183163.webp"}, {"id": "3768121", "title": "\u72af\u7f6a\u73b0\u573a\u8c03\u67e5\uff1a\u7ebd\u7ea6 \u7b2c\u4e09\u5b63", "original_title": "CSI: NY Season 3", "year": "2006", "is_tv": true, "rating": {"count": 2306, "max": 10, "star_count": 4.5, "value": 9.0}, "poster": "https://img9.doubanio.com/view/photo/m_ratio_poster/public/p2334071769.webp"}]}